src/__init__.py
src/pyak.py
pyak-0.0.3.dist-info/LICENSE
pyak-0.0.3.dist-info/METADATA
pyak-0.0.3.dist-info/WHEEL
pyak-0.0.3.dist-info/entry_points.txt
pyak-0.0.3.dist-info/top_level.txt
pyak-0.0.3.dist-info/RECORD
