Metadata-Version: 2.1
Name: pyak
Version: 0.0.3
Summary: A Python cli tools to automically press a key after some time interval.
Home-page: https://github.com/nyu058/pyak
Author: Nathan Yu
Author-email: nathan5508@gmail.com
License: UNKNOWN
Platform: UNKNOWN
Classifier: Programming Language :: Python :: 3
Classifier: License :: OSI Approved :: MIT License
Classifier: Operating System :: MacOS
Requires-Python: >=3.5
Requires-Dist: psutil
Requires-Dist: pyautogui
